{"id":990,"guid":"kI_q5eUMgJyu8GwXIsYEdQ","title":"حرب الكواكب!","tagline":"بلوتو .. كوكب شقي صغير","published_at":"2015-03-24T19:54:57.657Z","published":true,"updated_at":"2017-02-23T05:52:47.699Z","slug":"حرب-الكواكب","publication_slug":null,"recommendations_count":1,"comments_count":4,"pickabilities_count":0,"reading_time":9,"current_user_can_edit":null,"json_model":null,"created_at":"2015-03-24T19:39:40.562Z","followers_count":0,"hotness":259.5849625,"body":"<p class=\" guid-tagged\" title=\"8e0ff683-d970-4d22-bdf7-c7c301d331ee\"><i>نُشِرَ هذا المقال في سبتمبر 2006 على موقع عشرينات قبل اختطافه إداريا.</i><br></p><p class=\"guid-tagged\" title=\"d7294e56-6b1f-4d52-8dc9-573ca004c4d2\">\r\nفي صمت الفضاء السحيق \r\nيقف مخرجا لسانه لكل سكان كوكب الأرض، بعد أن فجر أزمة نجحت في إحداث \"حرب \r\nكواكب\" حقيقية هذه المرة بين علماء الفلك الأرضيين بالرغم من صغر حجمه \r\nالشديد!</p><p class=\"guid-tagged\" title=\"3df6d878-d05d-45da-bec3-ef8b335699a3\">\r\n</p><p class=\"guid-tagged\" title=\"76654030-ef24-4a57-9dd4-93e8bac229a4\">\r\n</p><p class=\"guid-tagged\" title=\"9afb6195-c480-4205-9d6d-8d4039698cda\">\r\n</p><p class=\"guid-tagged\" title=\"8c82bb1c-66ab-4fd6-a7db-c0168f9fc625\">\r\n </p><p class=\"guid-tagged\" title=\"e0587791-d58a-45a0-a89f-4fa6b7ad0dbc\">\r\n</p><p class=\"guid-tagged\" title=\"91017da9-fb51-4c4e-9b6a-f9bfc42a374c\">\r\n</p><p class=\"guid-tagged\" title=\"7eb079d9-eb7e-4f15-b4b1-fdb073f34be9\">\r\n</p><p class=\"guid-tagged\" title=\"9d15bad0-4848-44c3-a86f-fe76debba0ed\">\r\n</p><p class=\"guid-tagged\" title=\"30e2704d-be08-4d62-97a8-c7b5258615df\">\r\n</p><p class=\"guid-tagged\" title=\"e49a8563-8364-4488-ac74-6c186292e38a\">\r\nبلوتو (Pluto) –مفجر هذه الأزمة- اكتشفه الفلكي الأمريكي \"كلايد تومبو\" في أحد عمليات استكشاف الأجرام السماوية عام 1930 م،\r\n وهو كوكب يعادل حجمه ثلثي (2/3) حجم القمر التابع لكوكبنا حيث يبلغ قطره \r\n1430 ميلا -أي 2301 كيلو مترا-،اليوم على سطحه يعادل 6 أيام و9 ساعات \r\nأرضية، والسنة تعادل 248 سنة بتوقيتنا الأرضي، ويبعد عن شمسنا 39 ضعفا عما نبعد عنها نحن!(1)</p><p class=\"guid-tagged\" title=\"26de8439-b486-4ba6-ad1e-dd4ca455f76b\">\r\n</p><p class=\"guid-tagged\" title=\"fc6572ec-5956-4580-801e-e7bf9cf23f9f\">\r\n</p><p class=\"guid-tagged\" title=\"d7f5318f-db17-4ac9-9dc1-494112501e58\">\r\n</p><p class=\"guid-tagged\" title=\"4b84cc32-5415-4a52-ac9f-3f5287585de4\">\r\n </p><p class=\"guid-tagged\" title=\"6e99e973-c653-4f8c-b075-6390af1da776\">\r\n</p><p class=\"guid-tagged\" title=\"f8603921-f3ec-4bb8-876b-25b1b37b8abe\">\r\n</p><p class=\"guid-tagged\" title=\"2ddc2bc1-dbf5-406d-84bc-bea8719ad867\">\r\n</p><figure class=\" guid-tagged\" title=\"906a7615-2bb1-4a1b-92ba-6ca95740be03\"><img src=\"http://dsi4xlu0p7t9b.cloudfront.net/media/W1siZiIsIjIwMTUvMDMvMjUvMTIvMzEvMzkvNTEvQ2x5ZGVUb21iYXVnaDIuZ2lmIl1d/ClydeTombaugh2.gif\"></figure><p class=\"guid-tagged\" title=\"b248dc18-ac24-4ab9-8dcb-608407fac2f8\">\r\nبدأت الأزمة بعد انتهاء مؤتمر الفلكيين الدوليين IAU -الذي لابد أن معظمنا سمع عنه- حيث كان المقرر أن يقوم العلماء\r\n فيه بتحديد مصير لقب بلوتو \"الكوكبي\"، هل سيظل بلوتو كوكبا أم سيصنف على \r\nأنه نوع آخر من الأجرام الفضائية، وانتهى المؤتمر باتفاق \"الموجودين\" على \r\nإسقاط اللقب عن بلوتو ووضع تعريف جديد لمفهوم كلمة \"كوكب\" يتمثل بشكل رئيسي\r\n في وجود نوعين منه (كواكب-Planets) و(كواكب أقزام-Dwarf Planets)!!</p><p class=\"guid-tagged\" title=\"83e2405d-7758-4e02-a233-7d9cff2f0cab\">\r\n</p><p class=\"guid-tagged\" title=\"908ad2b9-4319-48ac-add4-6e8f7df0dfdb\">\r\n</p><p class=\"guid-tagged\" title=\"7bf11b80-c6a6-4d1b-ba9c-2f63a631e6ef\">\r\n</p><p class=\"guid-tagged\" title=\"c03daf77-c231-47b1-b84b-04a11e440a81\">\r\n </p><p class=\"guid-tagged\" title=\"0bf7f09d-ff43-4b94-875e-1cb32a508cd5\">\r\n</p><p class=\"guid-tagged\" title=\"ac35826c-dd05-458a-b694-26448c452d86\">\r\n</p><p class=\"guid-tagged\" title=\"d97bc1af-cdde-4ec4-8f0d-ad7a38597c8e\">\r\n</p><figure class=\" guid-tagged\" title=\"80d8e6fc-1035-4e16-aba3-5d791af129d7\"><img src=\"http://dsi4xlu0p7t9b.cloudfront.net/media/W1siZiIsIjIwMTUvMDMvMjUvMTIvMzEvMjIvODAwL2lhdV92b3Rpbmdfb25fcGx1dG9fZGVzdGlueS5qcGciXV0/iau%20voting%20on%20pluto%20destiny.jpg\"></figure><p class=\"guid-tagged\" title=\"2c8600d7-6d2a-4da9-862f-1a8584b8af41\">\r\nأثار هذا الأمر جدلا \r\nواسعا في الرأي العام العالمي – وهو أمر طبيعي-؛ عن تأثير هذا على المناهج \r\nالدراسية وما تعلموه طوال حياتهم و تربوا و نشئوا عليه، و انقسموا ما بين \r\nمؤيد ومعارض ومحايد.</p><p class=\"guid-tagged\" title=\"3073fd1c-c2ad-47d8-94f1-53b128c3cbd0\">\r\n</p><p class=\"guid-tagged\" title=\"24059808-0794-49e0-bf8a-f464cd094afb\">\r\n</p><p class=\"guid-tagged\" title=\"462a3c79-1c86-432c-bd18-7b702644602d\">\r\n</p><p class=\"guid-tagged\" title=\"aae6b6c1-36ba-47bc-bf60-f5abe2a9f267\">\r\n </p><p class=\"guid-tagged\" title=\"195e6361-3e34-46d9-a47b-5ac2ee1ff644\">\r\n</p><p class=\"guid-tagged\" title=\"bc147187-ae59-453f-8667-e8584ae864a1\">\r\n</p><p class=\"guid-tagged\" title=\"41aeb6ce-0046-498e-a989-1a7bd4469a36\">\r\n</p><p class=\"guid-tagged\" title=\"506e0b57-f7fc-45e3-a71c-ddeac7e97efd\">\r\n(آن مينارد) في <a href=\"http://news.nationalgeographic.com/news/2006/08/060830-pluto-planet.html?source=rss\" target=\"_blank\">المقال</a> الذي نشرته لتغطية الخبر على موقع <a href=\"http://www.nationalgeographic.com/\" target=\"_blank\">National Geographic News</a>\r\n حاولت أن تكون محايدة و لكنها لم تستطع كتمان تلك النبرة من الاستنكار في \r\nعنوان مقالها \"ماذا عسانا نخبر الأطفال؟!\"، أما \"جون جيبسون\" من Fox News فلم يكتف بالتلميح و اعترض صراحة في <a href=\"http://www.foxnews.com/story/0,2933,210358,00.html\" target=\"_blank\">مقاله</a> و بشكل ساخر تماما معلنا لهم أن يفعلوا ما يحلو لهم فبلوتو سيظل في نظره كوكبا و لا شيء يجبره على تغيير قناعاته..</p><p class=\"guid-tagged\" title=\"a5bae6b6-ef1d-47f2-a77a-477fa29e9953\">\r\n</p><p class=\"guid-tagged\" title=\"1fb9e410-699c-41e2-b4ed-d310be153c11\">\r\n</p><p class=\"guid-tagged\" title=\"77503470-369d-4fbf-afe0-86c6ddf53e0d\">\r\n</p><p class=\"guid-tagged\" title=\"fa676791-cf37-43f8-bdea-bbdcd7d79d9d\">\r\n </p><p class=\"guid-tagged\" title=\"c369f440-00e7-4e28-a4c9-0fac884f0b16\">\r\n</p><p class=\"guid-tagged\" title=\"60f76fa0-b783-4a5d-aac9-52b1f9850bd8\">\r\n</p><p class=\"guid-tagged\" title=\"756ddee6-d042-48bd-99ee-f44ca5651973\">\r\n</p><p class=\"guid-tagged\" title=\"d58bbeed-c949-4889-9a0e-faaa0a68b71d\">\r\nأما كارل ماثيوز -مؤلف موسيقي- أصيب بالإحباط الشديد عندما علم بالخبر و هو في مطار روما، فكارل كان قد ألف مقطوعة موسيقية سماها \"Pluto\"عام 2000، و أضافها إلى مجموعة\r\n من سبع مقطوعات موسيقية تمثل الكواكب السبع الأخرى غير الأرض آنذاك ألفها \r\nجوستاف هولست عام 1917 بعنوان \"الكواكب\"، و قال كارل ماثيوز \"كنت أعلم أن ذلك قد يحدث .. حيث أنه كان هناك جدل كبير بشأن حجم\r\n بلوتو .. ولكن على الأقل كان كوكبا حينما كتبت المقطوعة\"، ويبدو أن \r\nالمقطوعة الموسيقية (بلوتو) كتب لها البقاء -على الأقل للتاريخ- بعد أن \r\nقررت أحد الشركات تسجيلها وستعزفها أوركسترا برلين \"الفيلهارموني\" بقيادة \"سيمون راتال\".</p><p class=\"guid-tagged\" title=\"7981ded8-5a6b-4a71-91ff-e3947f1b68de\">\r\n</p><p class=\"guid-tagged\" title=\"445ae675-5948-4000-8394-0ae98d3dd913\">\r\n</p><p class=\"guid-tagged\" title=\"c3e21e8c-acda-432f-838f-ff60c2ec37eb\">\r\n</p><p class=\"guid-tagged\" title=\"34b7c730-78cb-4afc-928b-979890ebeacb\">\r\n </p><p class=\"guid-tagged\" title=\"2d121d7f-6609-462e-8669-cf9a2b9f0dee\">\r\n</p><p class=\"guid-tagged\" title=\"312976a5-dd0c-4d5c-b251-6b952000af8f\">\r\n</p><p class=\"guid-tagged\" title=\"fff4b37a-f881-4601-b6e2-9dabdefbaad5\">\r\n</p><p class=\"guid-tagged\" title=\"cf69c558-dc83-4550-bcbc-806d87907b59\">\r\nو ظهرت آثار هذا الجدل في أوضح صوره في عالم المدونات الالكترونية، فمثلا كتبت <a href=\"http://www.blogger.com/profile/28391822\" target=\"_blank\">دولمان</a> في مدونة \"<a href=\"http://echelonpress.blogspot.com/\" target=\"_blank\">هيا نتحدث عن ...</a>\" تحت عنوان \"<a href=\"http://echelonpress.blogspot.com/2006/09/dont-feel-sorry-for-pluto.html\" target=\"_blank\">لا تشعروا بالحزن لأجل بلوتو</a>\"\r\n أنه قد أدى دوره و ترك بصمة واضحة في تاريخ مجرتنا في زمن تتغير فيه \r\nالظروف و المعطيات بـ\"سرعة الضوء\"، و على غرار \"هايل هتلر\" أطلق أحد \r\nالمدونين الفلبينيين تحية \"<a href=\"http://philippinecommentary.blogspot.com/2006/09/hail-pluto-king-of-dwarf-planets.html\" target=\"_blank\">هايل بلوتو .. ملك الكواكب القزمة و حزام كويبر و المذنبات!!</a>\" مقتنعا و مرحبا بالتصنيف الفلكي الجديد!</p><p class=\"guid-tagged\" title=\"6165f34e-8d65-40c7-9d76-b52409525573\">\r\n</p><p class=\"guid-tagged\" title=\"334a84a3-faa3-4a7b-b32f-3f72948dc3eb\">\r\n</p><p class=\"guid-tagged\" title=\"f728f0e2-72d2-451b-9024-0968bcccd0fb\">\r\n</p><p class=\"guid-tagged\" title=\"74e99534-92f1-4aae-b9a6-3f286cc3ebdd\">\r\n </p><p class=\"guid-tagged\" title=\"fe2fc445-587c-49c4-a279-a7807da6ccc3\">\r\n</p><p class=\"guid-tagged\" title=\"37bc9eaf-4aca-4c32-be96-024d7c05269f\">\r\n</p><p class=\"guid-tagged\" title=\"21a82134-5ca8-4526-81ff-498b0279a634\">\r\n</p><p class=\"guid-tagged\" title=\"e7b56fd5-7440-4b2f-ba3a-6d6ead28374e\">\r\nو أبرز ردود الأفعال تلك رد فعل \"إيريك\" حيث أنشأ <a href=\"http://www.votepluto.com/\" target=\"_blank\">موقعا الكترونيا</a>\r\n لإعادة انتخاب بلوتو كوكبا تاسعا لمجموعتنا الشمسية! ولم يكتف بهذا بل وضع\r\n لافتات في حديقة منزله من أجل حملته! ولمشاهدة المزيد من ردود أفعال \r\nالمدونين كل ما عليك أن تدخل على موقع <a href=\"http://search.blogger.com/\" target=\"_blank\">search.blogger.com</a> التابع لجوجل و اكتب كلمة Pluto في خانة البحث و ستجد مئات النتائج.</p><p class=\"guid-tagged\" title=\"2e1a2369-45bd-4a6e-a6d2-a0ba83377d6a\">\r\n</p><p class=\"guid-tagged\" title=\"2f9cd673-20b7-4c68-b014-7d9bfe4cd47d\">\r\n</p><p class=\"guid-tagged\" title=\"65a6d380-df34-4c98-9709-1b62ab03f8aa\">\r\n</p><p class=\"guid-tagged\" title=\"1e24a144-c513-42d5-88db-3d7e60251cc2\">\r\n </p><p class=\"guid-tagged\" title=\"18d52c11-a9e6-4ead-98dd-5d413b0a22a3\">\r\n</p><p class=\"guid-tagged\" title=\"e7a0949f-7761-43d4-aa2b-c7381fe1a227\">\r\n</p><p class=\"guid-tagged\" title=\"7daa19c1-f9ee-40e3-9ccc-8b1c322b4463\">\r\n</p><p class=\"guid-tagged\" title=\"2441c772-686b-4330-be33-a8b4b44d45f6\">\r\nالعجيب أنه لم تكن هناك\r\n ردود فعل عربية ذات وزن يذكر، و هو ما يجعلنا نتسائل هل لا يهمنا أمر \r\n\"الكون\" و المجرة التي نعيش بها إلى هذا الحد؟!و هل هو \"كونهم\" هم و لا \r\nعلاقة لنا به؟!</p><p class=\"guid-tagged\" title=\"209b2b6b-3e8c-4f9f-8f40-5f50045432ba\">\r\n</p><p class=\"guid-tagged\" title=\"57e46511-b7b1-4bf1-b5e8-ed0eb028531b\">\r\n</p><p class=\"guid-tagged\" title=\"6e408148-c4c7-40c8-bf4a-cff46e67dfa5\">\r\n</p><p class=\"guid-tagged\" title=\"78feb24f-d1d6-400b-b30c-1dd5176e9827\">\r\n </p><p class=\"guid-tagged\" title=\"85ac1b8a-a343-40c0-831e-4763f2f6d86e\">\r\n</p><p class=\"guid-tagged\" title=\"71855424-a62a-4703-981b-47f91cb61163\">\r\n</p><p class=\"guid-tagged\" title=\"9facad3d-f473-4728-aef3-fff9de7d5684\">\r\n</p><h2 class=\"guid-tagged\" title=\"232b38e3-d145-4d79-8435-1da3c0bf9fbb\">\r\nعودة الـ\"بلوتو\"!</h2><p class=\"guid-tagged\" title=\"13ab0e73-3bc4-428a-bbc0-0359882e9823\">\r\n</p><p class=\"guid-tagged\" title=\"21b4b0b6-41c8-492e-8032-2f10ae11e173\">\r\n</p><p class=\"guid-tagged\" title=\"382eaf51-dd38-4913-914a-00b1fc78425d\">\r\n</p><p class=\"guid-tagged\" title=\"18ebde23-68c6-40a4-b254-0dc74f889f5f\">\r\n </p><p class=\"guid-tagged\" title=\"dd4bb7e8-7252-4be0-9172-ec211939158f\">\r\n</p><p class=\"guid-tagged\" title=\"dd0f6ebc-0743-4b41-a83e-eca2b8f9738a\">\r\n</p><p class=\"guid-tagged\" title=\"fde3267f-87e5-4968-b1bf-4f6d035633d5\">\r\n</p><p class=\"guid-tagged\" title=\"65092447-2f67-4193-8c6d-dfa732f15f4e\">\r\nو يبدو أن \"إيريك\" و \r\n\"كارل\" و كل محبي بلوتو قد يفرحون قريبا مرة أخرى، فقد وصلت الأزمة قمتها \r\nعندما بدأت مجموعة أخرى من العلماء حملة مضادة عنيفة على هذا القرار، فهم \r\nيرون أن تلاعبا تم في عملية التصويت و قالوا في بيان <a href=\"http://www.ipetitions.com/petition/planetprotest/\" target=\"_blank\">حملتهم لجمع توقيعات</a> علماء الفلك المعارضين أن 428 عالما فقط هم من قاموا بالتصويت من أصل 10,000 أعضاء تقريبا باتحاد الفلكيين الدوليين! و هو ما يفتح الباب للتساؤل عن \"الفساد العلمي\".</p><p class=\"guid-tagged\" title=\"1d5cc0c8-45fa-4f8b-86b5-a566a53999d4\">\r\n</p><p class=\"guid-tagged\" title=\"3eaf52f8-49ab-4779-b589-ece667fa30e9\">\r\n</p><p class=\"guid-tagged\" title=\"24c4775d-8415-4713-b86f-52cf558a5b79\">\r\n</p><p class=\"guid-tagged\" title=\"d4c830c1-3842-4d5e-a7a4-ae62424e8833\">\r\n </p><p class=\"guid-tagged\" title=\"835e832a-ed87-4dad-b5bc-f3b2fae2aaed\">\r\n</p><p class=\"guid-tagged\" title=\"61cb346d-ea0f-4720-b73a-707dc0b5f046\">\r\n</p><p class=\"guid-tagged\" title=\"08ff2481-5b65-432c-82c1-582b8350cd88\">\r\n</p><p class=\"guid-tagged\" title=\"57448cfd-33e7-435f-bc98-a0c251032e1a\">\r\nو في أقل من خمسة أيام،\r\n وصل عدد الموقعين على عريضة الاحتجاج هذه 300 عالما من بينهم أشخاص قاموا \r\nبدراسة كل كوكب و كويكب في مجموعتنا الشمسية بالإضافة إلى حزام كويبر، و \r\nبعضهم شارك في حملات استكشاف مجموعتنا الشمسية التي تمت باستخدام الروبوت، و\r\n بوصولهم إلى هذا العدد أغلق المنظمون العريضة معتبرين أنها أدت دورها و \r\nأوضحت رسالتهم جيدا للاتحاد، إلا أنهم ظلوا متمسكين بموقفهم : <br></p><blockquote class=\" guid-tagged\" title=\"35b3af5f-945a-4041-8266-de437f332eec\">We, as planetary scientists and \r\nastronomers, do not agree with the IAU's definition of a planet, nor \r\nwill we use it. A better definition is needed.<br></blockquote><hr contenteditable=\"false\"><p class=\"guid-tagged\" title=\"3585e9a3-70ba-4de8-ab77-0602fdb044ad\">وترجمتها إلى العربية :&nbsp;</p><blockquote class=\" guid-tagged\" title=\"9967c197-7181-430b-8f2d-925f8d9bb276\">نحن كعلماء فلك و كواكب لا نوافق على التعريف الجديد الذي أقره اتحاد الفلكيين الدوليين و لن نستخدمه، و نصر على ضرورة وجود تعريف جديد.</blockquote><p class=\"guid-tagged\" title=\"4a0e4b04-27a4-469a-90d3-490848a9ca12\"></p><h2 class=\"guid-tagged\" title=\"74599329-3fd3-49b8-9a90-f7b316766124\">تاريخ مثير لكوكب صغير</h2><p class=\"guid-tagged\" title=\"9e8e971a-9609-4442-8064-c91b9ec475c2\">\r\n</p><p class=\"guid-tagged\" title=\"70d794af-95cd-4213-9963-8e437ec1e483\">\r\n</p><p class=\"guid-tagged\" title=\"0fbf387a-2e0f-4c12-ac7a-08df939f0d0a\">\r\n</p><p class=\"guid-tagged\" title=\"db9166cb-18ce-4797-b2b6-4df3c9fbd589\">\r\n </p><p class=\"guid-tagged\" title=\"2b4ae8dd-72f6-4024-8836-7d0ba10b0489\">\r\n</p><p class=\"guid-tagged\" title=\"27f29e1b-df46-4052-911e-3aa101fd0d00\">\r\n</p><p class=\"guid-tagged\" title=\"ab85e0ad-efcd-4dbd-942f-d55d15f5d67b\">\r\n</p><p class=\"guid-tagged\" title=\"821e76d2-5a91-4831-b535-6154399383f8\">\r\nهذه\r\n الأزمة ليست غريبة على بلوتو بالرغم من صغر حجمه، فتاريخه أقل ما يوصف به \r\nأنه مثير، نبدأ باسمه الذي اختارته له فتاة عمرها آنذاك 11 عاما! كان يملك \r\nالحق في تسميته ساعتها  معهد لويل للبحث الفلكي و\r\n مديره \"فيستو ميلفن سليفر\" الذي طلب منه \"كلايد تومبو\" -مكتشف الكوكب- أن \r\nيقترح له اسما بسرعة قبل أن يفعل ذلك شخص آخر، و اقترحت مطلقته اسم \"زيوس Zeus\" ثم \"لويل Lowell\" و أخيرا اقترحت اسمها، و لم يلق أي منهم القبول، و تم اقتراح أسماء أخرى مثل \"كروناس Cronus\" و \"مينريفا Minerva\" و كانا مرشحين بقوة، و طرح الاسم \"بلوتو Pluto\" لأول مرة فتاة من أوكسفورد في بريطانيا اسمها \"فينيتيا باير Venetia Phair\" في حوار مع جدها فالكونر مادان أحد العاملين بمكتبة تابعة لجامعة أوكسفورد الذي بدوره قام بتمريره إلى الدكتور \"هيربرت هول تيرنر Herbert Hall Turner\" ليصل إلى زملائه في أمريكا، و بعد مناقشات مثيرة استقر به المطاف اسما للكوكب الأول من مايو 1930.</p><p class=\"guid-tagged\" title=\"2223dd20-9d59-481f-b84d-5eb2ebb9c99c\">\r\n</p><p class=\"guid-tagged\" title=\"aa569e7e-17eb-4f59-9ff7-c9c7561c44f4\">\r\n</p><p class=\"guid-tagged\" title=\"19cd8f6b-5777-4567-88ba-eb5158accee3\">\r\n</p><p class=\"guid-tagged\" title=\"8813ed8f-f867-400a-a91a-d36a523ec62a\">\r\n </p><p class=\"guid-tagged\" title=\"835cdb0c-c5dc-4a6f-be60-c1c6178c08fd\">\r\n</p><p class=\"guid-tagged\" title=\"9c216832-81b2-4833-9805-765379cc7fd3\">\r\n</p><p class=\"guid-tagged\" title=\"7c5a456e-0f2e-4c1f-92d6-479eec528126\">\r\n</p><figure class=\" guid-tagged\" title=\"d0a6ac3f-978b-4825-92f0-ceedc03abae4\"><img src=\"http://dsi4xlu0p7t9b.cloudfront.net/media/W1siZiIsIjIwMTUvMDMvMjUvMTIvMzgvMzEvNDAwL1ZlbmV0aWFfcGhhaXIuanBnIl1d/Venetia_phair.jpg\"></figure><p class=\"guid-tagged\" title=\"88fca920-2068-46b4-9864-deb5a9cd02ca\">\r\nو يتميز الاسم بدلالات كثيرة، فهو مكافئ للفظ الروماني “Hades” و الذي يعني \"غير معروف المنشأ\"، و يخلد اسم إله الرومان Pluto ، و يحمل الحروف الأولى من الفلكي المعروف Percival Lowell، و في كل من اللغات الصينية و اليابانية و الكورية يعني \"نجمة ملك الموت  Star of the King of the Dead\"، و في اللغة الفيتنامية هو اسم آخر لياما Yama أو حارس جهنم كما يعتقدون في المعتقدات الهندوسية!</p><p class=\"guid-tagged\" title=\"936c9bb9-7b6b-45af-aac4-4b7a30e14eeb\">\r\n</p><p class=\"guid-tagged\" title=\"2c7179a9-0d7d-4a7a-96a4-2e3021d4a17a\">\r\n</p><p class=\"guid-tagged\" title=\"c52af0c1-76d3-47c8-a5a0-4465b96013e0\">\r\n</p><p class=\"guid-tagged\" title=\"b7c56ba0-6b9d-4fb1-919b-c724b1d49c2a\">\r\n </p><p class=\"guid-tagged\" title=\"2116ef97-513b-4cac-93e1-e26c945b2fb3\">\r\n</p><p class=\"guid-tagged\" title=\"b49a02d1-63cc-4e17-a611-4f489830ddbc\">\r\n</p><p class=\"guid-tagged\" title=\"c01cc87e-5658-442d-8d69-743dcd437242\">\r\n</p><p class=\"guid-tagged\" title=\"96298a96-08c7-432b-9b07-1564262d2690\">\r\nبلوتو ذلك الكوكب غير \r\nالمعروف النشأة و الذي تختلف طبيعته عن بقية كواكب مجموعتنا الشمسية بعد \r\nاكتشافه مباشرة توقع العلماء أنه سيتفتت في غضون عشر سنوات على الأكثر، إلا\r\n أنهم فوجئوا به يزداد كثافة و قوة مما جعلهم يعيدون حساباتهم أكثر من مرة،\r\n و يستسلموا للحيرة بعدها!</p><p class=\"guid-tagged\" title=\"7145c768-76de-4615-abed-bc5d74fa9caf\">\r\n</p><p class=\"guid-tagged\" title=\"ce890923-6105-43ee-841b-51c7f9b9eab6\">\r\n</p><p class=\"guid-tagged\" title=\"25a031f9-795d-4357-a5ec-4b03dcbea5cc\">\r\n</p><p class=\"guid-tagged\" title=\"4784194d-861d-4c46-998f-4707e00165e6\">\r\n</p><p class=\"guid-tagged\" title=\"61691418-61ae-4efc-a7f0-45d86b0bb0de\">\r\n</p><p class=\"guid-tagged\" title=\"f967c1b4-5475-4acf-a70e-44317cfdb177\">\r\n </p><p class=\"guid-tagged\" title=\"33c072dd-c3e7-4157-b832-f20c0ad3426e\">\r\n</p><p class=\"guid-tagged\" title=\"6963eba4-cfb0-46fd-87cd-7272ee99fe65\">\r\n</p><p class=\"guid-tagged\" title=\"f6606ce7-7397-4d0b-954a-be5bbfd18527\">\r\n</p><p class=\"guid-tagged\" title=\"52a43f4f-a18b-4854-ad9c-97473b472703\">\r\n </p><p class=\"guid-tagged\" title=\"68359598-1c44-4d1f-85db-046964fa0b38\">\r\n</p><p class=\"guid-tagged\" title=\"477de9c4-f54c-4670-8d4b-da4a9bd658d8\">\r\n</p><p class=\"guid-tagged\" title=\"61ddd21d-0637-497d-a4b4-29a62233941b\">\r\n</p><p class=\"guid-tagged\" title=\"35a972e5-564a-4708-a37a-2d9a256c2380\">\r\n </p><p class=\"guid-tagged\" title=\"cef15978-4db5-40b3-a75c-d3023a69c14e\">\r\n</p><p class=\"guid-tagged\" title=\"5c7e4251-8ba4-44b3-b402-fddbd76bd4b2\">\r\n</p><p class=\"guid-tagged\" title=\"e5a56fc9-801b-4c2a-9851-23ff104c99fc\">\r\n</p><p class=\"guid-tagged\" title=\"3ed25fba-e417-4141-bff1-4bf633be5d6d\">\r\n </p><p class=\"guid-tagged\" title=\"22901a8c-0dfd-4681-a32d-a39e13bcffa5\">\r\n</p><p class=\"guid-tagged\" title=\"9f6c7514-9260-417d-9b66-f53094d33c11\">\r\n</p><p class=\"guid-tagged\" title=\"3f61e1e6-6f1e-402f-927f-391959e47c2f\">\r\n</p><p class=\"guid-tagged\" title=\"b6637d02-4e16-4faa-bc2f-baac00bf73ff\">\r\n </p><p class=\"guid-tagged\" title=\"4a62fcbf-5224-44b3-92fd-568b168e00cf\">\r\n</p><p class=\"guid-tagged\" title=\"3a8534f2-4d76-4a14-91c7-0fd0308eb22b\">\r\n</p><p class=\"guid-tagged\" title=\"2cd24e42-a585-44e9-ad8d-f40fceab49f8\">\r\n</p><p class=\"guid-tagged\" title=\"795fecb8-f3db-4d50-8cf3-05987802ac33\">\r\n </p><p class=\"guid-tagged\" title=\"7d17f1be-f187-4580-a09f-6eb730df6c80\">\r\n</p><p class=\"guid-tagged\" title=\"2e20368b-e38b-4325-9ac9-b4e92dd5d472\">\r\n</p><p class=\"guid-tagged\" title=\"f91e3a88-5a1a-4425-adbd-e0b5a2d1edd0\">\r\n</p><p class=\"guid-tagged\" title=\"4ff0dc84-1c87-4861-99e2-0de22620264e\">\r\n </p><p class=\"guid-tagged\" title=\"769bcdb0-44cf-45df-b4d3-798d4d2bd645\">\r\n</p><p class=\"guid-tagged\" title=\"1b27d69a-9f1c-4dfc-8123-3ec3d129e5ed\">\r\n</p><p class=\"guid-tagged\" title=\"bb164ebd-6d40-44b8-9052-359f131ae93e\">\r\n</p><p class=\"guid-tagged\" title=\"9d2f191d-c583-478e-acec-d8c926c06273\">\r\n </p><p class=\"guid-tagged\" title=\"eb0bdf99-1b78-4126-acaa-fd04a7993499\">\r\n</p><p class=\"guid-tagged\" title=\"5bc3f3c3-36e7-446b-81a5-502e7a0e856c\">\r\n</p><p class=\"guid-tagged\" title=\"44d37587-74cb-43bd-8ccb-506c23d105d8\">\r\n</p><p class=\"guid-tagged\" title=\"52b52625-0dbf-4efc-8ee1-7d9b86af43a3\">\r\n </p><p class=\"guid-tagged\" title=\"27356845-a498-44bd-b033-dce821bbd6ae\">\r\n</p><p class=\"guid-tagged\" title=\"3a48ee47-4fb4-443e-9bce-1b5f3d62910b\">\r\n</p><p class=\"guid-tagged\" title=\"b68cf882-9ea5-4818-b414-31bc947ff21f\">\r\n</p><p class=\"guid-tagged\" title=\"d0d1f419-52ec-4d7b-87eb-5dc0e36a24a3\">\r\n </p><p class=\"guid-tagged\" title=\"0c646c23-d929-41b6-a691-def589b06c6a\">\r\n</p><p class=\"guid-tagged\" title=\"96665512-5baa-4805-8f85-38404706d8be\">\r\n</p><p class=\"guid-tagged\" title=\"65da60f4-01ca-4493-aaef-3e6003823d87\">\r\n</p><figure class=\" guid-tagged\" title=\"ad4050a5-54f2-4bab-b56e-8470fd5c2a23\"><img src=\"http://dsi4xlu0p7t9b.cloudfront.net/media/W1siZiIsIjIwMTUvMDMvMjUvMTIvMzgvNDUvNzA3L3BsdXRvX2FuZF9jaGFyb24uanBnIl1d/pluto%20and%20charon.jpg\"></figure><p class=\"guid-tagged\" title=\"df1017a4-1173-4498-8963-701a41eda272\">\r\n\"تشارون Charon\"،\r\n هو اسم القمر الرئيسي لبلوتو، و مقارنة بحجمه فهو ضخم، هو الآخر أثار دهشة\r\n العديد من العلماء، و لم يكتفي الشقي الصغير بلوتو بذلك فقط، بل فجأة \r\nاكتشف العلماء أن هناك قمرين آخرين يدوران حوله! و صرح أحدهم لإحدى الصحف \r\nإثر هذا الاكتشاف \"إنه نظام كامل هناك\"!</p><p class=\"guid-tagged\" title=\"c05f0fca-f512-4f55-9c8b-7928e17f7000\">\r\n</p><p class=\"guid-tagged\" title=\"4e702c5f-fa27-44c9-863d-fe6f4d7b33a7\">\r\n</p><p class=\"guid-tagged\" title=\"59df98cf-0b30-42d8-ab2c-603869df0c65\">\r\n</p><p class=\"guid-tagged\" title=\"ebff8efa-a2b4-4783-99ab-ae3b3a2b7102\">\r\n </p><p class=\"guid-tagged\" title=\"8430cfd2-d60b-47ce-b2da-879adfb442b6\">\r\n</p><p class=\"guid-tagged\" title=\"da9d9006-8ff4-4b23-a06b-71f7aa48b2d7\">\r\n</p><p class=\"guid-tagged\" title=\"591f8007-ecfe-4511-badc-2eec909694f5\">\r\n</p><p class=\"guid-tagged\" title=\"61a4bd12-e3cc-4a61-b47f-63f21c9fff3f\">\r\nو كان بلوتو في البدء \r\nالكوكب الثامن في بعده عن الشمس، إلى أن تقاطع مداره مع مدار كوكب نبتون و \r\nتخطاه ليصبح ترتيبه التاسع! و يتوقع العلماء أنه سيطل كذلك لمدة 228 عاما \r\nعلى الأقل منذ تخطيه لنبتون في تسعينات القرن الماضي!</p><p class=\"guid-tagged\" title=\"5adfae2a-c0b2-4267-8385-15e7276f0f66\">\r\n</p><p class=\"guid-tagged\" title=\"46524af4-43f3-47d8-a64f-5cdb1e24d8ea\">\r\n</p><p class=\"guid-tagged\" title=\"f32ac22d-0357-400d-a3ae-5309d8c892e8\">\r\n</p><p class=\"guid-tagged\" title=\"252e91ab-f0c9-4391-abb9-b16a99959db3\">\r\n </p><p class=\"guid-tagged\" title=\"202332da-bc29-46a1-a7bf-f7b75fe32531\">\r\n</p><p class=\"guid-tagged\" title=\"910b62cf-307a-45f3-b442-5180471f4a67\">\r\n</p><p class=\"guid-tagged\" title=\"ab80a46f-d690-41f8-8a56-6d1e33729431\">\r\n</p><p class=\"guid-tagged\" title=\"4dd2b96b-470f-4349-bfd8-6d4d7cc88966\">\r\nعلى أي حال، نحن لا \r\nنملك إلا الانتظار لما ستسفر عنه الأيام القادمة من مفاجآت أخرى سواء كان \r\nصانعها \"بلوتو\" أو \"حرب الكواكب\" الدائرة بين علماء كوكبنا الآن..</p><p class=\"guid-tagged\" title=\"cb37d0ae-8deb-4999-8408-5abfb0030633\">\r\n-----</p><p class=\"guid-tagged\" title=\"71afc518-ef34-4684-a08e-a4efd868cda8\">\r\n</p><p class=\"guid-tagged\" title=\"55d76eea-b8a1-48a9-9b9b-f176f3c0e170\">\r\n</p><p class=\"guid-tagged\" title=\"75d1551d-b781-4ab8-81d7-cff928f5379c\">\r\n</p><p class=\"guid-tagged\" title=\"04f546fb-ffd4-4795-9e7d-b712c3ea8823\">\r\n(1) للمزيد من المعلومات عن بلوتو : <a href=\"http://www.space.com/scienceastronomy/solarsystem/pluto-ez.html\" target=\"_blank\">اضغط هنا</a> لتطالع صفحته على موقع <a href=\"http://www.space.com/\" target=\"_blank\">space.com</a><br></p><p class=\"guid-tagged\" title=\"291bf47d-a300-4c13-8c22-586c4d1fec2f\"><br></p><p class=\"guid-tagged\" title=\"10b92441-e643-4878-81a8-e1e06d9382c1\">\r\n</p><p class=\"guid-tagged\" title=\"439f7f69-8934-4281-9958-960904f34e5a\">\r\n</p><p class=\"guid-tagged\" title=\"7853e081-ceb2-4352-851c-b5ce56c8a7d5\">\r\n</p><p class=\"guid-tagged\" title=\"4fce0951-0278-4b83-aa69-8897dc102e91\"><i>ملحوظة 1 : صورة المقال <br></i></p><p class=\"guid-tagged\" title=\"add43be2-06da-431e-89d1-6103cf7a09ac\"><i>ملحوظة 2 : لم أتابع تطورات القضية بعد هذه النقطة، هذا المقال نشر في سبتمبر 2006، من المرجح بقوة أن تكون هناك تطورات لم أرصدها.</i><br></p><p class=\" guid-tagged\" title=\"826b5d17-cb7c-4bf2-81b6-ba191d86269f\">\r\n      </p>","articles":[{"id":986,"guid":"Bz0V0nez-QQR0Wx3nERzMQ","title":"Shortcuts","tagline":"نشرت هذه التدوينة على مدونتي في يونيو 2008","published_at":"2015-03-24T18:19:22.988Z","published":true,"updated_at":"2017-02-23T05:52:47.613Z","slug":"shortcuts","publication_slug":null,"recommendations_count":2,"comments_count":1,"pickabilities_count":0,"reading_time":1,"thumbs_srcs":[],"thumbs_srcsets":[],"user":{"id":768,"name":"مُصْعَب إِبْرَاهِيم","published_articles_count":13,"nickname":"mos3abof","thumb_url":"https://api.manshar.com/media/W1siZiIsIjIwMTYvMDgvMTEvMTEvNTQvMDMvNjI4L3Bob3RvLmpwZyJdLFsicCIsInRodW1iIiwiNDAweDQwMCMiXV0/photo.jpg","followed_by_current_user":null,"follows_current_user":null,"current_user_pickability":null},"publication":null,"followed_by_current_user":null,"current_user_pickability":null,"topic":{"id":25,"title":"سرد ذاتي","category":{"id":6,"color":"#aa1133"}}}],"user":{"id":768,"name":"مُصْعَب إِبْرَاهِيم","published_articles_count":13,"nickname":"mos3abof","bio":"وَضَعُوهُ عِنْدَ مُفْتَرَقِ طَرِيقَيْنِ وَخَيَّرُوْه، شَقَّ طَرِيقَاً جَدِيْداً في المُنْتَصَفِ وَقَالَ لَهُمْ : \"لَمْ أَعْتَدِ الطُّرَقَ مُمَهَّدَةً\".","created_at":"2015-03-24T10:12:30.952Z","admin":false,"editor":false,"comments_count":5,"recommendations_count":3,"followers_count":40,"following_users_count":0,"created_nickname_at":"2017-08-01T14:22:26.569Z","pickabilities_count":1,"avatar_url":"https://api.manshar.com/media/W1siZiIsIjIwMTYvMDgvMTEvMTEvNTQvMDMvNjI4L3Bob3RvLmpwZyJdXQ/photo.jpg","thumb_url":"https://api.manshar.com/media/W1siZiIsIjIwMTYvMDgvMTEvMTEvNTQvMDMvNjI4L3Bob3RvLmpwZyJdLFsicCIsInRodW1iIiwiNDAweDQwMCMiXV0/photo.jpg","followed_by_current_user":null,"follows_current_user":null,"current_user_pickability":null,"profiles":{"twitter":{"uid":"610343","provider":"twitter","nickname":"mos3abof"},"gplus":{"uid":"103548894461701347059","provider":"gplus","nickname":null},"facebook":{"uid":"10155177148376047","provider":"facebook","nickname":"mos3"}},"cover_url":"https://api.manshar.com/media/W1siZiIsIjIwMTYvMDgvMTEvMTEvNTQvMDMvNjI4L3Bob3RvLmpwZyJdLFsicCIsInRodW1iIiwiMTkwMHgxMjAwIyJdXQ/photo.jpg"},"publication":null,"topic":{"id":62,"title":"المجرة الشمسية","articles_count":1,"followers_count":0,"pickabilities_count":0,"created_at":"2015-03-24T19:53:46.745Z","updated_at":"2015-03-24T19:53:46.745Z","category":{"id":1,"title":"علوم وتكنولوجيا","color":"#03A9F4","icon_cssclass":"fa-desktop","created_at":"2015-01-20T07:47:50.785Z","updated_at":"2015-02-02T04:45:52.579Z","articles_count":340,"topics_count":128,"description":"مواضيع حول العلوم المختلفة، الأحياء، الفيزياء، تكنولوجيا وغيرها","followers_count":31,"original_image_url":"https://api.manshar.com/media/W1siZiIsIjIwMTUvMDIvMDIvMDQvNDUvNTIvNDIyL2NvbXB1dGVyXzgyMzcxXzEyODAuanBnIl1d","followed_by_current_user":null,"image_thumb_url":"https://api.manshar.com/media/W1siZiIsIjIwMTUvMDIvMDIvMDQvNDUvNTIvNDIyL2NvbXB1dGVyXzgyMzcxXzEyODAuanBnIl0sWyJwIiwidGh1bWIiLCI4MHg4MCMiXV0","icon_url":null},"followed_by_current_user":null},"followed_by_current_user":null,"current_user_pickability":null,"tags":[{"id":57,"title":"المجرة الشمسية","slug":"المجرة-الشمسية","articles_count":0,"followers_count":0,"pickabilities_count":0,"followed_by_current_user":null,"current_user_pickability":null}]}