[{"id":1990,"guid":"b3wsvyde","body":"بعمري ما طلبت منهم بعدلوها 😂. شكلك كاينة مغلباهم! 😂😂","created_at":"2017-07-04T22:49:55.813Z","updated_at":"2017-07-04T22:49:55.813Z","pickabilities_count":0,"user":{"id":1,"name":"محمد خطيب","published_articles_count":25,"nickname":"mk","thumb_url":"https://api.manshar.com/media/W1siZiIsIjIwMTQvMTIvMDkvMTEvNTIvNDUvOTk3L1dHMUE5MzU3LmpwZyJdLFsicCIsInRodW1iIiwiNDAweDQwMCMiXV0/WG1A9357.jpg","followed_by_current_user":null,"follows_current_user":null,"current_user_pickability":null}}]